b_rabbit/__init__.py
b_rabbit/b_rabbit.py
b_rabbit/logging.ini
b_rabbit-1.2.5.dist-info/AUTHORS.rst
b_rabbit-1.2.5.dist-info/LICENSE
b_rabbit-1.2.5.dist-info/METADATA
b_rabbit-1.2.5.dist-info/WHEEL
b_rabbit-1.2.5.dist-info/top_level.txt
b_rabbit-1.2.5.dist-info/RECORD
