Metadata-Version: 2.1
Name: b-rabbit
Version: 1.2.5
Summary: An abstract interface for RabbitMQ communication
Home-page: https://github.com/nidhaloff/b_rabbit
Author: Nidhal Baccouri
Author-email: nidhalbacc@gmail.com
License: MIT license
Keywords: b_rabbit,rabbitmq,RabbitMQ,Microservices,SOA,MQTT,AMQP,Queues,Messaging queue,queue messaging,publish-subscribe,publish-pattern,subscribe-pattern,publish messaging,subscribe messaging,remote procedure call,RPC
Platform: UNKNOWN
Classifier: Development Status :: 4 - Beta
Classifier: Intended Audience :: Developers
Classifier: Intended Audience :: Education
Classifier: Intended Audience :: Information Technology
Classifier: Intended Audience :: System Administrators
Classifier: Intended Audience :: Telecommunications Industry
Classifier: Operating System :: OS Independent
Classifier: Topic :: Communications
Classifier: Topic :: Home Automation
Classifier: Topic :: Internet :: Log Analysis
Classifier: Topic :: Software Development
Classifier: Topic :: System :: Networking
Classifier: License :: OSI Approved :: MIT License
Classifier: Natural Language :: English
Classifier: Programming Language :: Python :: 3
Classifier: Programming Language :: Python :: 3.5
Classifier: Programming Language :: Python :: 3.6
Classifier: Programming Language :: Python :: 3.7
Classifier: Programming Language :: Python :: 3.8
Requires-Python: >=3.4
License-File: LICENSE
License-File: AUTHORS.rst
